[
  {
    "date": "2024-12-01",
    "price": 2540.88227272727,
    "unit": "USD/metric ton",
    "quality": "high",
    "source": "fred",
    "sourceId": "PALUMUSDM",
    "fetchedAt": "2025-12-15T07:37:33.422Z"
  },
  {
    "date": "2024-11-01",
    "price": 2582.18857142857,
    "unit": "USD/metric ton",
    "quality": "high",
    "source": "fred",
    "sourceId": "PALUMUSDM",
    "fetchedAt": "2025-12-15T07:37:33.422Z"
  },
  {
    "date": "2024-10-01",
    "price": 2595.58304347826,
    "unit": "USD/metric ton",
    "quality": "high",
    "source": "fred",
    "sourceId": "PALUMUSDM",
    "fetchedAt": "2025-12-15T07:37:33.422Z"
  },
  {
    "date": "2024-09-01",
    "price": 2457.4780952381,
    "unit": "USD/metric ton",
    "quality": "high",
    "source": "fred",
    "sourceId": "PALUMUSDM",
    "fetchedAt": "2025-12-15T07:37:33.422Z"
  },
  {
    "date": "2024-08-01",
    "price": 2352.46727272727,
    "unit": "USD/metric ton",
    "quality": "high",
    "source": "fred",
    "sourceId": "PALUMUSDM",
    "fetchedAt": "2025-12-15T07:37:33.422Z"
  },
  {
    "date": "2024-07-01",
    "price": 2349.1252173913,
    "unit": "USD/metric ton",
    "quality": "high",
    "source": "fred",
    "sourceId": "PALUMUSDM",
    "fetchedAt": "2025-12-15T07:37:33.422Z"
  },
  {
    "date": "2024-06-01",
    "price": 2497.6055,
    "unit": "USD/metric ton",
    "quality": "high",
    "source": "fred",
    "sourceId": "PALUMUSDM",
    "fetchedAt": "2025-12-15T07:37:33.422Z"
  },
  {
    "date": "2024-05-01",
    "price": 2566.31869565217,
    "unit": "USD/metric ton",
    "quality": "high",
    "source": "fred",
    "sourceId": "PALUMUSDM",
    "fetchedAt": "2025-12-15T07:37:33.422Z"
  },
  {
    "date": "2024-04-01",
    "price": 2499.22818181818,
    "unit": "USD/metric ton",
    "quality": "high",
    "source": "fred",
    "sourceId": "PALUMUSDM",
    "fetchedAt": "2025-12-15T07:37:33.422Z"
  },
  {
    "date": "2024-03-01",
    "price": 2229.4419047619,
    "unit": "USD/metric ton",
    "quality": "high",
    "source": "fred",
    "sourceId": "PALUMUSDM",
    "fetchedAt": "2025-12-15T07:37:33.422Z"
  },
  {
    "date": "2024-02-01",
    "price": 2179.45714285714,
    "unit": "USD/metric ton",
    "quality": "high",
    "source": "fred",
    "sourceId": "PALUMUSDM",
    "fetchedAt": "2025-12-15T07:37:33.422Z"
  },
  {
    "date": "2024-01-01",
    "price": 2201.56652173913,
    "unit": "USD/metric ton",
    "quality": "high",
    "source": "fred",
    "sourceId": "PALUMUSDM",
    "fetchedAt": "2025-12-15T07:37:33.422Z"
  }
]