[
  {
    "date": "2026-01-01",
    "price": 14.074458,
    "unit": "usd/kilogram",
    "source": "fred",
    "sourceId": "PWOOLFUSDM",
    "quality": "high",
    "fetchedAt": "2026-03-08T23:10:39.712Z"
  },
  {
    "date": "2025-12-01",
    "price": 12.663263,
    "unit": "usd/kilogram",
    "source": "fred",
    "sourceId": "PWOOLFUSDM",
    "quality": "high",
    "fetchedAt": "2026-03-08T23:10:39.712Z"
  },
  {
    "date": "2025-11-01",
    "price": 11.779487,
    "unit": "usd/kilogram",
    "source": "fred",
    "sourceId": "PWOOLFUSDM",
    "quality": "high",
    "fetchedAt": "2026-03-08T23:10:39.712Z"
  },
  {
    "date": "2025-10-01",
    "price": 11.68983,
    "unit": "usd/kilogram",
    "source": "fred",
    "sourceId": "PWOOLFUSDM",
    "quality": "high",
    "fetchedAt": "2026-03-08T23:10:39.712Z"
  },
  {
    "date": "2025-09-01",
    "price": 10.963048,
    "unit": "usd/kilogram",
    "source": "fred",
    "sourceId": "PWOOLFUSDM",
    "quality": "high",
    "fetchedAt": "2026-03-08T23:10:39.712Z"
  },
  {
    "date": "2025-08-01",
    "price": 9.936778,
    "unit": "usd/kilogram",
    "source": "fred",
    "sourceId": "PWOOLFUSDM",
    "quality": "high",
    "fetchedAt": "2026-03-08T23:10:39.712Z"
  },
  {
    "date": "2025-07-01",
    "price": 9.831709,
    "unit": "usd/kilogram",
    "source": "fred",
    "sourceId": "PWOOLFUSDM",
    "quality": "high",
    "fetchedAt": "2026-03-08T23:10:39.712Z"
  },
  {
    "date": "2025-06-01",
    "price": 9.866639,
    "unit": "usd/kilogram",
    "source": "fred",
    "sourceId": "PWOOLFUSDM",
    "quality": "high",
    "fetchedAt": "2026-03-08T23:10:39.712Z"
  },
  {
    "date": "2025-05-01",
    "price": 9.845668,
    "unit": "usd/kilogram",
    "source": "fred",
    "sourceId": "PWOOLFUSDM",
    "quality": "high",
    "fetchedAt": "2026-03-08T23:10:39.712Z"
  },
  {
    "date": "2025-04-01",
    "price": 9.710929,
    "unit": "usd/kilogram",
    "source": "fred",
    "sourceId": "PWOOLFUSDM",
    "quality": "high",
    "fetchedAt": "2026-03-08T23:10:39.712Z"
  },
  {
    "date": "2025-03-01",
    "price": 9.734509,
    "unit": "usd/kilogram",
    "source": "fred",
    "sourceId": "PWOOLFUSDM",
    "quality": "high",
    "fetchedAt": "2026-03-08T23:10:39.712Z"
  },
  {
    "date": "2025-02-01",
    "price": 9.337912,
    "unit": "usd/kilogram",
    "source": "fred",
    "sourceId": "PWOOLFUSDM",
    "quality": "high",
    "fetchedAt": "2026-03-08T23:10:39.712Z"
  },
  {
    "date": "2025-01-01",
    "price": 9.15591,
    "unit": "usd/kilogram",
    "source": "fred",
    "sourceId": "PWOOLFUSDM",
    "quality": "high",
    "fetchedAt": "2026-03-08T23:10:39.712Z"
  },
  {
    "date": "2024-12-01",
    "price": 9.055296,
    "unit": "usd/kilogram",
    "source": "fred",
    "sourceId": "PWOOLFUSDM",
    "quality": "high",
    "fetchedAt": "2026-03-08T23:10:39.712Z"
  },
  {
    "date": "2024-11-01",
    "price": 9.169265,
    "unit": "usd/kilogram",
    "source": "fred",
    "sourceId": "PWOOLFUSDM",
    "quality": "high",
    "fetchedAt": "2026-03-08T23:10:39.712Z"
  },
  {
    "date": "2024-10-01",
    "price": 9.369981,
    "unit": "usd/kilogram",
    "source": "fred",
    "sourceId": "PWOOLFUSDM",
    "quality": "high",
    "fetchedAt": "2026-03-08T23:10:39.712Z"
  },
  {
    "date": "2024-09-01",
    "price": 9.102677,
    "unit": "usd/kilogram",
    "source": "fred",
    "sourceId": "PWOOLFUSDM",
    "quality": "high",
    "fetchedAt": "2026-03-08T23:10:39.712Z"
  },
  {
    "date": "2024-08-01",
    "price": 9.136283,
    "unit": "usd/kilogram",
    "source": "fred",
    "sourceId": "PWOOLFUSDM",
    "quality": "high",
    "fetchedAt": "2026-03-08T23:10:39.712Z"
  },
  {
    "date": "2024-07-01",
    "price": 9.13561,
    "unit": "usd/kilogram",
    "source": "fred",
    "sourceId": "PWOOLFUSDM",
    "quality": "high",
    "fetchedAt": "2026-03-08T23:10:39.712Z"
  },
  {
    "date": "2024-06-01",
    "price": 9.439427,
    "unit": "usd/kilogram",
    "source": "fred",
    "sourceId": "PWOOLFUSDM",
    "quality": "high",
    "fetchedAt": "2026-03-08T23:10:39.712Z"
  },
  {
    "date": "2024-05-01",
    "price": 9.278487,
    "unit": "usd/kilogram",
    "source": "fred",
    "sourceId": "PWOOLFUSDM",
    "quality": "high",
    "fetchedAt": "2026-03-08T23:10:39.712Z"
  },
  {
    "date": "2024-04-01",
    "price": 9.259809,
    "unit": "usd/kilogram",
    "source": "fred",
    "sourceId": "PWOOLFUSDM",
    "quality": "high",
    "fetchedAt": "2026-03-08T23:10:39.712Z"
  },
  {
    "date": "2024-03-01",
    "price": 9.335147,
    "unit": "usd/kilogram",
    "source": "fred",
    "sourceId": "PWOOLFUSDM",
    "quality": "high",
    "fetchedAt": "2026-03-08T23:10:39.712Z"
  },
  {
    "date": "2024-02-01",
    "price": 9.211751,
    "unit": "usd/kilogram",
    "source": "fred",
    "sourceId": "PWOOLFUSDM",
    "quality": "high",
    "fetchedAt": "2026-03-08T23:10:39.712Z"
  },
  {
    "date": "2024-01-01",
    "price": 9.700218,
    "unit": "usd/kilogram",
    "source": "fred",
    "sourceId": "PWOOLFUSDM",
    "quality": "high",
    "fetchedAt": "2026-03-08T23:10:39.712Z"
  },
  {
    "date": "2023-12-01",
    "price": 9.834548,
    "unit": "usd/kilogram",
    "source": "fred",
    "sourceId": "PWOOLFUSDM",
    "quality": "high",
    "fetchedAt": "2026-03-08T23:10:39.712Z"
  },
  {
    "date": "2023-11-01",
    "price": 9.311157,
    "unit": "usd/kilogram",
    "source": "fred",
    "sourceId": "PWOOLFUSDM",
    "quality": "high",
    "fetchedAt": "2026-03-08T23:10:39.712Z"
  },
  {
    "date": "2023-10-01",
    "price": 8.940868,
    "unit": "usd/kilogram",
    "source": "fred",
    "sourceId": "PWOOLFUSDM",
    "quality": "high",
    "fetchedAt": "2026-03-08T23:10:39.712Z"
  },
  {
    "date": "2023-09-01",
    "price": 9.07559,
    "unit": "usd/kilogram",
    "source": "fred",
    "sourceId": "PWOOLFUSDM",
    "quality": "high",
    "fetchedAt": "2026-03-08T23:10:39.712Z"
  },
  {
    "date": "2023-08-01",
    "price": 9.326027,
    "unit": "usd/kilogram",
    "source": "fred",
    "sourceId": "PWOOLFUSDM",
    "quality": "high",
    "fetchedAt": "2026-03-08T23:10:39.712Z"
  },
  {
    "date": "2023-07-01",
    "price": 9.91867,
    "unit": "usd/kilogram",
    "source": "fred",
    "sourceId": "PWOOLFUSDM",
    "quality": "high",
    "fetchedAt": "2026-03-08T23:10:39.712Z"
  },
  {
    "date": "2023-06-01",
    "price": 9.81958,
    "unit": "usd/kilogram",
    "source": "fred",
    "sourceId": "PWOOLFUSDM",
    "quality": "high",
    "fetchedAt": "2026-03-08T23:10:39.712Z"
  },
  {
    "date": "2023-05-01",
    "price": 10.501057,
    "unit": "usd/kilogram",
    "source": "fred",
    "sourceId": "PWOOLFUSDM",
    "quality": "high",
    "fetchedAt": "2026-03-08T23:10:39.712Z"
  },
  {
    "date": "2023-04-01",
    "price": 10.865432,
    "unit": "usd/kilogram",
    "source": "fred",
    "sourceId": "PWOOLFUSDM",
    "quality": "high",
    "fetchedAt": "2026-03-08T23:10:39.712Z"
  },
  {
    "date": "2023-03-01",
    "price": 11.257422,
    "unit": "usd/kilogram",
    "source": "fred",
    "sourceId": "PWOOLFUSDM",
    "quality": "high",
    "fetchedAt": "2026-03-08T23:10:39.712Z"
  },
  {
    "date": "2023-02-01",
    "price": 11.92425,
    "unit": "usd/kilogram",
    "source": "fred",
    "sourceId": "PWOOLFUSDM",
    "quality": "high",
    "fetchedAt": "2026-03-08T23:10:39.712Z"
  },
  {
    "date": "2023-01-01",
    "price": 11.545005,
    "unit": "usd/kilogram",
    "source": "fred",
    "sourceId": "PWOOLFUSDM",
    "quality": "high",
    "fetchedAt": "2026-03-08T23:10:39.712Z"
  },
  {
    "date": "2022-12-01",
    "price": 10.61117,
    "unit": "usd/kilogram",
    "source": "fred",
    "sourceId": "PWOOLFUSDM",
    "quality": "high",
    "fetchedAt": "2026-03-08T23:10:39.712Z"
  },
  {
    "date": "2022-11-01",
    "price": 10.20359,
    "unit": "usd/kilogram",
    "source": "fred",
    "sourceId": "PWOOLFUSDM",
    "quality": "high",
    "fetchedAt": "2026-03-08T23:10:39.712Z"
  },
  {
    "date": "2022-10-01",
    "price": 10.048221,
    "unit": "usd/kilogram",
    "source": "fred",
    "sourceId": "PWOOLFUSDM",
    "quality": "high",
    "fetchedAt": "2026-03-08T23:10:39.712Z"
  },
  {
    "date": "2022-09-01",
    "price": 10.674166,
    "unit": "usd/kilogram",
    "source": "fred",
    "sourceId": "PWOOLFUSDM",
    "quality": "high",
    "fetchedAt": "2026-03-08T23:10:39.712Z"
  },
  {
    "date": "2022-08-01",
    "price": 11.247868,
    "unit": "usd/kilogram",
    "source": "fred",
    "sourceId": "PWOOLFUSDM",
    "quality": "high",
    "fetchedAt": "2026-03-08T23:10:39.712Z"
  },
  {
    "date": "2022-07-01",
    "price": 11.56697,
    "unit": "usd/kilogram",
    "source": "fred",
    "sourceId": "PWOOLFUSDM",
    "quality": "high",
    "fetchedAt": "2026-03-08T23:10:39.712Z"
  },
  {
    "date": "2022-06-01",
    "price": 12.531142,
    "unit": "usd/kilogram",
    "source": "fred",
    "sourceId": "PWOOLFUSDM",
    "quality": "high",
    "fetchedAt": "2026-03-08T23:10:39.712Z"
  },
  {
    "date": "2022-05-01",
    "price": 12.242495,
    "unit": "usd/kilogram",
    "source": "fred",
    "sourceId": "PWOOLFUSDM",
    "quality": "high",
    "fetchedAt": "2026-03-08T23:10:39.712Z"
  },
  {
    "date": "2022-04-01",
    "price": 12.420937,
    "unit": "usd/kilogram",
    "source": "fred",
    "sourceId": "PWOOLFUSDM",
    "quality": "high",
    "fetchedAt": "2026-03-08T23:10:39.712Z"
  },
  {
    "date": "2022-03-01",
    "price": 12.4176,
    "unit": "usd/kilogram",
    "source": "fred",
    "sourceId": "PWOOLFUSDM",
    "quality": "high",
    "fetchedAt": "2026-03-08T23:10:39.712Z"
  },
  {
    "date": "2022-02-01",
    "price": 12.34984,
    "unit": "usd/kilogram",
    "source": "fred",
    "sourceId": "PWOOLFUSDM",
    "quality": "high",
    "fetchedAt": "2026-03-08T23:10:39.712Z"
  },
  {
    "date": "2022-01-01",
    "price": 12.240971,
    "unit": "usd/kilogram",
    "source": "fred",
    "sourceId": "PWOOLFUSDM",
    "quality": "high",
    "fetchedAt": "2026-03-08T23:10:39.712Z"
  },
  {
    "date": "2021-12-01",
    "price": 11.962225,
    "unit": "usd/kilogram",
    "source": "fred",
    "sourceId": "PWOOLFUSDM",
    "quality": "high",
    "fetchedAt": "2026-03-08T23:10:39.712Z"
  },
  {
    "date": "2021-11-01",
    "price": 11.961735,
    "unit": "usd/kilogram",
    "source": "fred",
    "sourceId": "PWOOLFUSDM",
    "quality": "high",
    "fetchedAt": "2026-03-08T23:10:39.712Z"
  },
  {
    "date": "2021-10-01",
    "price": 12.270029,
    "unit": "usd/kilogram",
    "source": "fred",
    "sourceId": "PWOOLFUSDM",
    "quality": "high",
    "fetchedAt": "2026-03-08T23:10:39.712Z"
  },
  {
    "date": "2021-09-01",
    "price": 12.132611,
    "unit": "usd/kilogram",
    "source": "fred",
    "sourceId": "PWOOLFUSDM",
    "quality": "high",
    "fetchedAt": "2026-03-08T23:10:39.712Z"
  },
  {
    "date": "2021-08-01",
    "price": 12.185823,
    "unit": "usd/kilogram",
    "source": "fred",
    "sourceId": "PWOOLFUSDM",
    "quality": "high",
    "fetchedAt": "2026-03-08T23:10:39.712Z"
  },
  {
    "date": "2021-07-01",
    "price": 13.090747,
    "unit": "usd/kilogram",
    "source": "fred",
    "sourceId": "PWOOLFUSDM",
    "quality": "high",
    "fetchedAt": "2026-03-08T23:10:39.712Z"
  },
  {
    "date": "2021-06-01",
    "price": 13.38218,
    "unit": "usd/kilogram",
    "source": "fred",
    "sourceId": "PWOOLFUSDM",
    "quality": "high",
    "fetchedAt": "2026-03-08T23:10:39.712Z"
  },
  {
    "date": "2021-05-01",
    "price": 12.574183,
    "unit": "usd/kilogram",
    "source": "fred",
    "sourceId": "PWOOLFUSDM",
    "quality": "high",
    "fetchedAt": "2026-03-08T23:10:39.712Z"
  },
  {
    "date": "2021-04-01",
    "price": 12.242672,
    "unit": "usd/kilogram",
    "source": "fred",
    "sourceId": "PWOOLFUSDM",
    "quality": "high",
    "fetchedAt": "2026-03-08T23:10:39.712Z"
  },
  {
    "date": "2021-03-01",
    "price": 12.217892,
    "unit": "usd/kilogram",
    "source": "fred",
    "sourceId": "PWOOLFUSDM",
    "quality": "high",
    "fetchedAt": "2026-03-08T23:10:39.712Z"
  },
  {
    "date": "2021-02-01",
    "price": 12.253287,
    "unit": "usd/kilogram",
    "source": "fred",
    "sourceId": "PWOOLFUSDM",
    "quality": "high",
    "fetchedAt": "2026-03-08T23:10:39.712Z"
  },
  {
    "date": "2021-01-01",
    "price": 11.0376,
    "unit": "usd/kilogram",
    "source": "fred",
    "sourceId": "PWOOLFUSDM",
    "quality": "high",
    "fetchedAt": "2026-03-08T23:10:39.712Z"
  },
  {
    "date": "2020-12-01",
    "price": 10.475726,
    "unit": "usd/kilogram",
    "source": "fred",
    "sourceId": "PWOOLFUSDM",
    "quality": "high",
    "fetchedAt": "2026-03-08T23:10:39.712Z"
  },
  {
    "date": "2020-11-01",
    "price": 10.104887,
    "unit": "usd/kilogram",
    "source": "fred",
    "sourceId": "PWOOLFUSDM",
    "quality": "high",
    "fetchedAt": "2026-03-08T23:10:39.712Z"
  },
  {
    "date": "2020-10-01",
    "price": 9.335142,
    "unit": "usd/kilogram",
    "source": "fred",
    "sourceId": "PWOOLFUSDM",
    "quality": "high",
    "fetchedAt": "2026-03-08T23:10:39.712Z"
  },
  {
    "date": "2020-09-01",
    "price": 7.260246,
    "unit": "usd/kilogram",
    "source": "fred",
    "sourceId": "PWOOLFUSDM",
    "quality": "high",
    "fetchedAt": "2026-03-08T23:10:39.712Z"
  },
  {
    "date": "2020-08-01",
    "price": 8.012659,
    "unit": "usd/kilogram",
    "source": "fred",
    "sourceId": "PWOOLFUSDM",
    "quality": "high",
    "fetchedAt": "2026-03-08T23:10:39.712Z"
  },
  {
    "date": "2020-07-01",
    "price": 8.959679,
    "unit": "usd/kilogram",
    "source": "fred",
    "sourceId": "PWOOLFUSDM",
    "quality": "high",
    "fetchedAt": "2026-03-08T23:10:39.712Z"
  },
  {
    "date": "2020-06-01",
    "price": 9.160884,
    "unit": "usd/kilogram",
    "source": "fred",
    "sourceId": "PWOOLFUSDM",
    "quality": "high",
    "fetchedAt": "2026-03-08T23:10:39.712Z"
  },
  {
    "date": "2020-05-01",
    "price": 8.994792,
    "unit": "usd/kilogram",
    "source": "fred",
    "sourceId": "PWOOLFUSDM",
    "quality": "high",
    "fetchedAt": "2026-03-08T23:10:39.712Z"
  },
  {
    "date": "2020-04-01",
    "price": 9.373274,
    "unit": "usd/kilogram",
    "source": "fred",
    "sourceId": "PWOOLFUSDM",
    "quality": "high",
    "fetchedAt": "2026-03-08T23:10:39.712Z"
  },
  {
    "date": "2020-03-01",
    "price": 10.660984,
    "unit": "usd/kilogram",
    "source": "fred",
    "sourceId": "PWOOLFUSDM",
    "quality": "high",
    "fetchedAt": "2026-03-08T23:10:39.712Z"
  },
  {
    "date": "2020-02-01",
    "price": 12.24222,
    "unit": "usd/kilogram",
    "source": "fred",
    "sourceId": "PWOOLFUSDM",
    "quality": "high",
    "fetchedAt": "2026-03-08T23:10:39.712Z"
  },
  {
    "date": "2020-01-01",
    "price": 12.551804,
    "unit": "usd/kilogram",
    "source": "fred",
    "sourceId": "PWOOLFUSDM",
    "quality": "high",
    "fetchedAt": "2026-03-08T23:10:39.712Z"
  },
  {
    "date": "2019-12-01",
    "price": 12.077946,
    "unit": "usd/kilogram",
    "source": "fred",
    "sourceId": "PWOOLFUSDM",
    "quality": "high",
    "fetchedAt": "2026-03-08T23:10:39.712Z"
  },
  {
    "date": "2019-11-01",
    "price": 12.207995,
    "unit": "usd/kilogram",
    "source": "fred",
    "sourceId": "PWOOLFUSDM",
    "quality": "high",
    "fetchedAt": "2026-03-08T23:10:39.712Z"
  },
  {
    "date": "2019-10-01",
    "price": 12.171586,
    "unit": "usd/kilogram",
    "source": "fred",
    "sourceId": "PWOOLFUSDM",
    "quality": "high",
    "fetchedAt": "2026-03-08T23:10:39.712Z"
  },
  {
    "date": "2019-09-01",
    "price": 11.77632,
    "unit": "usd/kilogram",
    "source": "fred",
    "sourceId": "PWOOLFUSDM",
    "quality": "high",
    "fetchedAt": "2026-03-08T23:10:39.712Z"
  },
  {
    "date": "2019-08-01",
    "price": 12.252803,
    "unit": "usd/kilogram",
    "source": "fred",
    "sourceId": "PWOOLFUSDM",
    "quality": "high",
    "fetchedAt": "2026-03-08T23:10:39.712Z"
  },
  {
    "date": "2019-07-01",
    "price": 14.183186,
    "unit": "usd/kilogram",
    "source": "fred",
    "sourceId": "PWOOLFUSDM",
    "quality": "high",
    "fetchedAt": "2026-03-08T23:10:39.712Z"
  },
  {
    "date": "2019-06-01",
    "price": 14.71359,
    "unit": "usd/kilogram",
    "source": "fred",
    "sourceId": "PWOOLFUSDM",
    "quality": "high",
    "fetchedAt": "2026-03-08T23:10:39.712Z"
  },
  {
    "date": "2019-05-01",
    "price": 15.596152,
    "unit": "usd/kilogram",
    "source": "fred",
    "sourceId": "PWOOLFUSDM",
    "quality": "high",
    "fetchedAt": "2026-03-08T23:10:39.712Z"
  },
  {
    "date": "2019-04-01",
    "price": 16.366848,
    "unit": "usd/kilogram",
    "source": "fred",
    "sourceId": "PWOOLFUSDM",
    "quality": "high",
    "fetchedAt": "2026-03-08T23:10:39.712Z"
  },
  {
    "date": "2019-03-01",
    "price": 16.60465,
    "unit": "usd/kilogram",
    "source": "fred",
    "sourceId": "PWOOLFUSDM",
    "quality": "high",
    "fetchedAt": "2026-03-08T23:10:39.712Z"
  },
  {
    "date": "2019-02-01",
    "price": 16.897412,
    "unit": "usd/kilogram",
    "source": "fred",
    "sourceId": "PWOOLFUSDM",
    "quality": "high",
    "fetchedAt": "2026-03-08T23:10:39.712Z"
  },
  {
    "date": "2019-01-01",
    "price": 16.45678,
    "unit": "usd/kilogram",
    "source": "fred",
    "sourceId": "PWOOLFUSDM",
    "quality": "high",
    "fetchedAt": "2026-03-08T23:10:39.712Z"
  },
  {
    "date": "2018-12-01",
    "price": 16.028338,
    "unit": "usd/kilogram",
    "source": "fred",
    "sourceId": "PWOOLFUSDM",
    "quality": "high",
    "fetchedAt": "2026-03-08T23:10:39.712Z"
  },
  {
    "date": "2018-11-01",
    "price": 15.6496,
    "unit": "usd/kilogram",
    "source": "fred",
    "sourceId": "PWOOLFUSDM",
    "quality": "high",
    "fetchedAt": "2026-03-08T23:10:39.712Z"
  },
  {
    "date": "2018-10-01",
    "price": 16.523417,
    "unit": "usd/kilogram",
    "source": "fred",
    "sourceId": "PWOOLFUSDM",
    "quality": "high",
    "fetchedAt": "2026-03-08T23:10:39.712Z"
  },
  {
    "date": "2018-09-01",
    "price": 17.471236,
    "unit": "usd/kilogram",
    "source": "fred",
    "sourceId": "PWOOLFUSDM",
    "quality": "high",
    "fetchedAt": "2026-03-08T23:10:39.712Z"
  },
  {
    "date": "2018-08-01",
    "price": 17.401303,
    "unit": "usd/kilogram",
    "source": "fred",
    "sourceId": "PWOOLFUSDM",
    "quality": "high",
    "fetchedAt": "2026-03-08T23:10:39.712Z"
  },
  {
    "date": "2018-07-01",
    "price": 16.890949,
    "unit": "usd/kilogram",
    "source": "fred",
    "sourceId": "PWOOLFUSDM",
    "quality": "high",
    "fetchedAt": "2026-03-08T23:10:39.712Z"
  },
  {
    "date": "2018-06-01",
    "price": 17.396612,
    "unit": "usd/kilogram",
    "source": "fred",
    "sourceId": "PWOOLFUSDM",
    "quality": "high",
    "fetchedAt": "2026-03-08T23:10:39.712Z"
  },
  {
    "date": "2018-05-01",
    "price": 16.48876,
    "unit": "usd/kilogram",
    "source": "fred",
    "sourceId": "PWOOLFUSDM",
    "quality": "high",
    "fetchedAt": "2026-03-08T23:10:39.712Z"
  },
  {
    "date": "2018-04-01",
    "price": 15.991605,
    "unit": "usd/kilogram",
    "source": "fred",
    "sourceId": "PWOOLFUSDM",
    "quality": "high",
    "fetchedAt": "2026-03-08T23:10:39.712Z"
  },
  {
    "date": "2018-03-01",
    "price": 16.08184,
    "unit": "usd/kilogram",
    "source": "fred",
    "sourceId": "PWOOLFUSDM",
    "quality": "high",
    "fetchedAt": "2026-03-08T23:10:39.712Z"
  },
  {
    "date": "2018-02-01",
    "price": 16.838748,
    "unit": "usd/kilogram",
    "source": "fred",
    "sourceId": "PWOOLFUSDM",
    "quality": "high",
    "fetchedAt": "2026-03-08T23:10:39.712Z"
  },
  {
    "date": "2018-01-01",
    "price": 16.94038,
    "unit": "usd/kilogram",
    "source": "fred",
    "sourceId": "PWOOLFUSDM",
    "quality": "high",
    "fetchedAt": "2026-03-08T23:10:39.712Z"
  },
  {
    "date": "2017-12-01",
    "price": 15.590248,
    "unit": "usd/kilogram",
    "source": "fred",
    "sourceId": "PWOOLFUSDM",
    "quality": "high",
    "fetchedAt": "2026-03-08T23:10:39.712Z"
  },
  {
    "date": "2017-11-01",
    "price": 15.178953,
    "unit": "usd/kilogram",
    "source": "fred",
    "sourceId": "PWOOLFUSDM",
    "quality": "high",
    "fetchedAt": "2026-03-08T23:10:39.712Z"
  },
  {
    "date": "2017-10-01",
    "price": 14.63647,
    "unit": "usd/kilogram",
    "source": "fred",
    "sourceId": "PWOOLFUSDM",
    "quality": "high",
    "fetchedAt": "2026-03-08T23:10:39.712Z"
  },
  {
    "date": "2017-09-01",
    "price": 14.297214,
    "unit": "usd/kilogram",
    "source": "fred",
    "sourceId": "PWOOLFUSDM",
    "quality": "high",
    "fetchedAt": "2026-03-08T23:10:39.712Z"
  },
  {
    "date": "2017-08-01",
    "price": 14.705977,
    "unit": "usd/kilogram",
    "source": "fred",
    "sourceId": "PWOOLFUSDM",
    "quality": "high",
    "fetchedAt": "2026-03-08T23:10:39.712Z"
  },
  {
    "date": "2017-07-01",
    "price": 14.063609,
    "unit": "usd/kilogram",
    "source": "fred",
    "sourceId": "PWOOLFUSDM",
    "quality": "high",
    "fetchedAt": "2026-03-08T23:10:39.712Z"
  },
  {
    "date": "2017-06-01",
    "price": 14.038277,
    "unit": "usd/kilogram",
    "source": "fred",
    "sourceId": "PWOOLFUSDM",
    "quality": "high",
    "fetchedAt": "2026-03-08T23:10:39.712Z"
  },
  {
    "date": "2017-05-01",
    "price": 14.334653,
    "unit": "usd/kilogram",
    "source": "fred",
    "sourceId": "PWOOLFUSDM",
    "quality": "high",
    "fetchedAt": "2026-03-08T23:10:39.712Z"
  },
  {
    "date": "2017-04-01",
    "price": 14.009328,
    "unit": "usd/kilogram",
    "source": "fred",
    "sourceId": "PWOOLFUSDM",
    "quality": "high",
    "fetchedAt": "2026-03-08T23:10:39.712Z"
  },
  {
    "date": "2017-03-01",
    "price": 14.548294,
    "unit": "usd/kilogram",
    "source": "fred",
    "sourceId": "PWOOLFUSDM",
    "quality": "high",
    "fetchedAt": "2026-03-08T23:10:39.712Z"
  },
  {
    "date": "2017-02-01",
    "price": 13.654441,
    "unit": "usd/kilogram",
    "source": "fred",
    "sourceId": "PWOOLFUSDM",
    "quality": "high",
    "fetchedAt": "2026-03-08T23:10:39.712Z"
  },
  {
    "date": "2017-01-01",
    "price": 13.05624,
    "unit": "usd/kilogram",
    "source": "fred",
    "sourceId": "PWOOLFUSDM",
    "quality": "high",
    "fetchedAt": "2026-03-08T23:10:39.712Z"
  },
  {
    "date": "2016-12-01",
    "price": 12.062082,
    "unit": "usd/kilogram",
    "source": "fred",
    "sourceId": "PWOOLFUSDM",
    "quality": "high",
    "fetchedAt": "2026-03-08T23:10:39.712Z"
  },
  {
    "date": "2016-11-01",
    "price": 11.892833,
    "unit": "usd/kilogram",
    "source": "fred",
    "sourceId": "PWOOLFUSDM",
    "quality": "high",
    "fetchedAt": "2026-03-08T23:10:39.712Z"
  },
  {
    "date": "2016-10-01",
    "price": 11.869199,
    "unit": "usd/kilogram",
    "source": "fred",
    "sourceId": "PWOOLFUSDM",
    "quality": "high",
    "fetchedAt": "2026-03-08T23:10:39.712Z"
  },
  {
    "date": "2016-09-01",
    "price": 11.473969,
    "unit": "usd/kilogram",
    "source": "fred",
    "sourceId": "PWOOLFUSDM",
    "quality": "high",
    "fetchedAt": "2026-03-08T23:10:39.711Z"
  },
  {
    "date": "2016-08-01",
    "price": 11.424911,
    "unit": "usd/kilogram",
    "source": "fred",
    "sourceId": "PWOOLFUSDM",
    "quality": "high",
    "fetchedAt": "2026-03-08T23:10:39.711Z"
  },
  {
    "date": "2016-07-01",
    "price": 11.38139,
    "unit": "usd/kilogram",
    "source": "fred",
    "sourceId": "PWOOLFUSDM",
    "quality": "high",
    "fetchedAt": "2026-03-08T23:10:39.711Z"
  },
  {
    "date": "2016-06-01",
    "price": 10.942102,
    "unit": "usd/kilogram",
    "source": "fred",
    "sourceId": "PWOOLFUSDM",
    "quality": "high",
    "fetchedAt": "2026-03-08T23:10:39.711Z"
  },
  {
    "date": "2016-05-01",
    "price": 10.967055,
    "unit": "usd/kilogram",
    "source": "fred",
    "sourceId": "PWOOLFUSDM",
    "quality": "high",
    "fetchedAt": "2026-03-08T23:10:39.711Z"
  },
  {
    "date": "2016-04-01",
    "price": 10.879192,
    "unit": "usd/kilogram",
    "source": "fred",
    "sourceId": "PWOOLFUSDM",
    "quality": "high",
    "fetchedAt": "2026-03-08T23:10:39.711Z"
  },
  {
    "date": "2016-03-01",
    "price": 10.358409,
    "unit": "usd/kilogram",
    "source": "fred",
    "sourceId": "PWOOLFUSDM",
    "quality": "high",
    "fetchedAt": "2026-03-08T23:10:39.711Z"
  },
  {
    "date": "2016-02-01",
    "price": 10.174158,
    "unit": "usd/kilogram",
    "source": "fred",
    "sourceId": "PWOOLFUSDM",
    "quality": "high",
    "fetchedAt": "2026-03-08T23:10:39.711Z"
  },
  {
    "date": "2016-01-01",
    "price": 10.133633,
    "unit": "usd/kilogram",
    "source": "fred",
    "sourceId": "PWOOLFUSDM",
    "quality": "high",
    "fetchedAt": "2026-03-08T23:10:39.711Z"
  },
  {
    "date": "2015-12-01",
    "price": 10.258673,
    "unit": "usd/kilogram",
    "source": "fred",
    "sourceId": "PWOOLFUSDM",
    "quality": "high",
    "fetchedAt": "2026-03-08T23:10:39.711Z"
  },
  {
    "date": "2015-11-01",
    "price": 10.024531,
    "unit": "usd/kilogram",
    "source": "fred",
    "sourceId": "PWOOLFUSDM",
    "quality": "high",
    "fetchedAt": "2026-03-08T23:10:39.711Z"
  },
  {
    "date": "2015-10-01",
    "price": 9.560591,
    "unit": "usd/kilogram",
    "source": "fred",
    "sourceId": "PWOOLFUSDM",
    "quality": "high",
    "fetchedAt": "2026-03-08T23:10:39.711Z"
  },
  {
    "date": "2015-09-01",
    "price": 9.667448,
    "unit": "usd/kilogram",
    "source": "fred",
    "sourceId": "PWOOLFUSDM",
    "quality": "high",
    "fetchedAt": "2026-03-08T23:10:39.711Z"
  },
  {
    "date": "2015-08-01",
    "price": 10.226808,
    "unit": "usd/kilogram",
    "source": "fred",
    "sourceId": "PWOOLFUSDM",
    "quality": "high",
    "fetchedAt": "2026-03-08T23:10:39.711Z"
  },
  {
    "date": "2015-07-01",
    "price": 10.221673,
    "unit": "usd/kilogram",
    "source": "fred",
    "sourceId": "PWOOLFUSDM",
    "quality": "high",
    "fetchedAt": "2026-03-08T23:10:39.711Z"
  },
  {
    "date": "2015-06-01",
    "price": 11.481251,
    "unit": "usd/kilogram",
    "source": "fred",
    "sourceId": "PWOOLFUSDM",
    "quality": "high",
    "fetchedAt": "2026-03-08T23:10:39.711Z"
  },
  {
    "date": "2015-05-01",
    "price": 11.145791,
    "unit": "usd/kilogram",
    "source": "fred",
    "sourceId": "PWOOLFUSDM",
    "quality": "high",
    "fetchedAt": "2026-03-08T23:10:39.711Z"
  },
  {
    "date": "2015-04-01",
    "price": 9.937329,
    "unit": "usd/kilogram",
    "source": "fred",
    "sourceId": "PWOOLFUSDM",
    "quality": "high",
    "fetchedAt": "2026-03-08T23:10:39.711Z"
  },
  {
    "date": "2015-03-01",
    "price": 9.294507,
    "unit": "usd/kilogram",
    "source": "fred",
    "sourceId": "PWOOLFUSDM",
    "quality": "high",
    "fetchedAt": "2026-03-08T23:10:39.711Z"
  },
  {
    "date": "2015-02-01",
    "price": 9.469113,
    "unit": "usd/kilogram",
    "source": "fred",
    "sourceId": "PWOOLFUSDM",
    "quality": "high",
    "fetchedAt": "2026-03-08T23:10:39.711Z"
  },
  {
    "date": "2015-01-01",
    "price": 9.6703,
    "unit": "usd/kilogram",
    "source": "fred",
    "sourceId": "PWOOLFUSDM",
    "quality": "high",
    "fetchedAt": "2026-03-08T23:10:39.711Z"
  },
  {
    "date": "2014-12-01",
    "price": 10.139329,
    "unit": "usd/kilogram",
    "source": "fred",
    "sourceId": "PWOOLFUSDM",
    "quality": "high",
    "fetchedAt": "2026-03-08T23:10:39.711Z"
  },
  {
    "date": "2014-11-01",
    "price": 10.419703,
    "unit": "usd/kilogram",
    "source": "fred",
    "sourceId": "PWOOLFUSDM",
    "quality": "high",
    "fetchedAt": "2026-03-08T23:10:39.711Z"
  },
  {
    "date": "2014-10-01",
    "price": 10.440121,
    "unit": "usd/kilogram",
    "source": "fred",
    "sourceId": "PWOOLFUSDM",
    "quality": "high",
    "fetchedAt": "2026-03-08T23:10:39.711Z"
  },
  {
    "date": "2014-09-01",
    "price": 10.565015,
    "unit": "usd/kilogram",
    "source": "fred",
    "sourceId": "PWOOLFUSDM",
    "quality": "high",
    "fetchedAt": "2026-03-08T23:10:39.711Z"
  },
  {
    "date": "2014-08-01",
    "price": 10.69751,
    "unit": "usd/kilogram",
    "source": "fred",
    "sourceId": "PWOOLFUSDM",
    "quality": "high",
    "fetchedAt": "2026-03-08T23:10:39.711Z"
  },
  {
    "date": "2014-07-01",
    "price": 10.781498,
    "unit": "usd/kilogram",
    "source": "fred",
    "sourceId": "PWOOLFUSDM",
    "quality": "high",
    "fetchedAt": "2026-03-08T23:10:39.711Z"
  },
  {
    "date": "2014-06-01",
    "price": 10.731732,
    "unit": "usd/kilogram",
    "source": "fred",
    "sourceId": "PWOOLFUSDM",
    "quality": "high",
    "fetchedAt": "2026-03-08T23:10:39.711Z"
  },
  {
    "date": "2014-05-01",
    "price": 10.968493,
    "unit": "usd/kilogram",
    "source": "fred",
    "sourceId": "PWOOLFUSDM",
    "quality": "high",
    "fetchedAt": "2026-03-08T23:10:39.711Z"
  },
  {
    "date": "2014-04-01",
    "price": 10.880174,
    "unit": "usd/kilogram",
    "source": "fred",
    "sourceId": "PWOOLFUSDM",
    "quality": "high",
    "fetchedAt": "2026-03-08T23:10:39.711Z"
  },
  {
    "date": "2014-03-01",
    "price": 10.775687,
    "unit": "usd/kilogram",
    "source": "fred",
    "sourceId": "PWOOLFUSDM",
    "quality": "high",
    "fetchedAt": "2026-03-08T23:10:39.711Z"
  },
  {
    "date": "2014-02-01",
    "price": 11.172059,
    "unit": "usd/kilogram",
    "source": "fred",
    "sourceId": "PWOOLFUSDM",
    "quality": "high",
    "fetchedAt": "2026-03-08T23:10:39.711Z"
  },
  {
    "date": "2014-01-01",
    "price": 11.472438,
    "unit": "usd/kilogram",
    "source": "fred",
    "sourceId": "PWOOLFUSDM",
    "quality": "high",
    "fetchedAt": "2026-03-08T23:10:39.711Z"
  },
  {
    "date": "2013-12-01",
    "price": 11.981497,
    "unit": "usd/kilogram",
    "source": "fred",
    "sourceId": "PWOOLFUSDM",
    "quality": "high",
    "fetchedAt": "2026-03-08T23:10:39.711Z"
  },
  {
    "date": "2013-11-01",
    "price": 11.89595,
    "unit": "usd/kilogram",
    "source": "fred",
    "sourceId": "PWOOLFUSDM",
    "quality": "high",
    "fetchedAt": "2026-03-08T23:10:39.711Z"
  },
  {
    "date": "2013-10-01",
    "price": 11.987204,
    "unit": "usd/kilogram",
    "source": "fred",
    "sourceId": "PWOOLFUSDM",
    "quality": "high",
    "fetchedAt": "2026-03-08T23:10:39.711Z"
  },
  {
    "date": "2013-09-01",
    "price": 11.590132,
    "unit": "usd/kilogram",
    "source": "fred",
    "sourceId": "PWOOLFUSDM",
    "quality": "high",
    "fetchedAt": "2026-03-08T23:10:39.711Z"
  },
  {
    "date": "2013-08-01",
    "price": 10.306305,
    "unit": "usd/kilogram",
    "source": "fred",
    "sourceId": "PWOOLFUSDM",
    "quality": "high",
    "fetchedAt": "2026-03-08T23:10:39.711Z"
  },
  {
    "date": "2013-07-01",
    "price": 10.252811,
    "unit": "usd/kilogram",
    "source": "fred",
    "sourceId": "PWOOLFUSDM",
    "quality": "high",
    "fetchedAt": "2026-03-08T23:10:39.711Z"
  },
  {
    "date": "2013-06-01",
    "price": 11.176655,
    "unit": "usd/kilogram",
    "source": "fred",
    "sourceId": "PWOOLFUSDM",
    "quality": "high",
    "fetchedAt": "2026-03-08T23:10:39.711Z"
  },
  {
    "date": "2013-05-01",
    "price": 11.580285,
    "unit": "usd/kilogram",
    "source": "fred",
    "sourceId": "PWOOLFUSDM",
    "quality": "high",
    "fetchedAt": "2026-03-08T23:10:39.711Z"
  },
  {
    "date": "2013-04-01",
    "price": 12.085929,
    "unit": "usd/kilogram",
    "source": "fred",
    "sourceId": "PWOOLFUSDM",
    "quality": "high",
    "fetchedAt": "2026-03-08T23:10:39.711Z"
  },
  {
    "date": "2013-03-01",
    "price": 13.240885,
    "unit": "usd/kilogram",
    "source": "fred",
    "sourceId": "PWOOLFUSDM",
    "quality": "high",
    "fetchedAt": "2026-03-08T23:10:39.711Z"
  },
  {
    "date": "2013-02-01",
    "price": 13.745908,
    "unit": "usd/kilogram",
    "source": "fred",
    "sourceId": "PWOOLFUSDM",
    "quality": "high",
    "fetchedAt": "2026-03-08T23:10:39.711Z"
  },
  {
    "date": "2013-01-01",
    "price": 13.931523,
    "unit": "usd/kilogram",
    "source": "fred",
    "sourceId": "PWOOLFUSDM",
    "quality": "high",
    "fetchedAt": "2026-03-08T23:10:39.711Z"
  },
  {
    "date": "2012-12-01",
    "price": 13.541554,
    "unit": "usd/kilogram",
    "source": "fred",
    "sourceId": "PWOOLFUSDM",
    "quality": "high",
    "fetchedAt": "2026-03-08T23:10:39.711Z"
  },
  {
    "date": "2012-11-01",
    "price": 12.593015,
    "unit": "usd/kilogram",
    "source": "fred",
    "sourceId": "PWOOLFUSDM",
    "quality": "high",
    "fetchedAt": "2026-03-08T23:10:39.711Z"
  },
  {
    "date": "2012-10-01",
    "price": 12.047629,
    "unit": "usd/kilogram",
    "source": "fred",
    "sourceId": "PWOOLFUSDM",
    "quality": "high",
    "fetchedAt": "2026-03-08T23:10:39.711Z"
  },
  {
    "date": "2012-09-01",
    "price": 11.494904,
    "unit": "usd/kilogram",
    "source": "fred",
    "sourceId": "PWOOLFUSDM",
    "quality": "high",
    "fetchedAt": "2026-03-08T23:10:39.711Z"
  },
  {
    "date": "2012-08-01",
    "price": 11.920815,
    "unit": "usd/kilogram",
    "source": "fred",
    "sourceId": "PWOOLFUSDM",
    "quality": "high",
    "fetchedAt": "2026-03-08T23:10:39.711Z"
  },
  {
    "date": "2012-07-01",
    "price": 12.975259,
    "unit": "usd/kilogram",
    "source": "fred",
    "sourceId": "PWOOLFUSDM",
    "quality": "high",
    "fetchedAt": "2026-03-08T23:10:39.711Z"
  },
  {
    "date": "2012-06-01",
    "price": 12.854211,
    "unit": "usd/kilogram",
    "source": "fred",
    "sourceId": "PWOOLFUSDM",
    "quality": "high",
    "fetchedAt": "2026-03-08T23:10:39.711Z"
  },
  {
    "date": "2012-05-01",
    "price": 13.403009,
    "unit": "usd/kilogram",
    "source": "fred",
    "sourceId": "PWOOLFUSDM",
    "quality": "high",
    "fetchedAt": "2026-03-08T23:10:39.711Z"
  },
  {
    "date": "2012-04-01",
    "price": 14.372204,
    "unit": "usd/kilogram",
    "source": "fred",
    "sourceId": "PWOOLFUSDM",
    "quality": "high",
    "fetchedAt": "2026-03-08T23:10:39.711Z"
  },
  {
    "date": "2012-03-01",
    "price": 15.395248,
    "unit": "usd/kilogram",
    "source": "fred",
    "sourceId": "PWOOLFUSDM",
    "quality": "high",
    "fetchedAt": "2026-03-08T23:10:39.711Z"
  },
  {
    "date": "2012-02-01",
    "price": 15.608229,
    "unit": "usd/kilogram",
    "source": "fred",
    "sourceId": "PWOOLFUSDM",
    "quality": "high",
    "fetchedAt": "2026-03-08T23:10:39.711Z"
  },
  {
    "date": "2012-01-01",
    "price": 15.020456,
    "unit": "usd/kilogram",
    "source": "fred",
    "sourceId": "PWOOLFUSDM",
    "quality": "high",
    "fetchedAt": "2026-03-08T23:10:39.711Z"
  },
  {
    "date": "2011-12-01",
    "price": 14.386442,
    "unit": "usd/kilogram",
    "source": "fred",
    "sourceId": "PWOOLFUSDM",
    "quality": "high",
    "fetchedAt": "2026-03-08T23:10:39.711Z"
  },
  {
    "date": "2011-11-01",
    "price": 14.69253,
    "unit": "usd/kilogram",
    "source": "fred",
    "sourceId": "PWOOLFUSDM",
    "quality": "high",
    "fetchedAt": "2026-03-08T23:10:39.711Z"
  },
  {
    "date": "2011-10-01",
    "price": 14.313263,
    "unit": "usd/kilogram",
    "source": "fred",
    "sourceId": "PWOOLFUSDM",
    "quality": "high",
    "fetchedAt": "2026-03-08T23:10:39.711Z"
  },
  {
    "date": "2011-09-01",
    "price": 15.931952,
    "unit": "usd/kilogram",
    "source": "fred",
    "sourceId": "PWOOLFUSDM",
    "quality": "high",
    "fetchedAt": "2026-03-08T23:10:39.711Z"
  },
  {
    "date": "2011-08-01",
    "price": 16.555856,
    "unit": "usd/kilogram",
    "source": "fred",
    "sourceId": "PWOOLFUSDM",
    "quality": "high",
    "fetchedAt": "2026-03-08T23:10:39.711Z"
  },
  {
    "date": "2011-07-01",
    "price": 17.759567,
    "unit": "usd/kilogram",
    "source": "fred",
    "sourceId": "PWOOLFUSDM",
    "quality": "high",
    "fetchedAt": "2026-03-08T23:10:39.711Z"
  },
  {
    "date": "2011-06-01",
    "price": 18.654394,
    "unit": "usd/kilogram",
    "source": "fred",
    "sourceId": "PWOOLFUSDM",
    "quality": "high",
    "fetchedAt": "2026-03-08T23:10:39.711Z"
  },
  {
    "date": "2011-05-01",
    "price": 17.92967,
    "unit": "usd/kilogram",
    "source": "fred",
    "sourceId": "PWOOLFUSDM",
    "quality": "high",
    "fetchedAt": "2026-03-08T23:10:39.711Z"
  },
  {
    "date": "2011-04-01",
    "price": 17.436731,
    "unit": "usd/kilogram",
    "source": "fred",
    "sourceId": "PWOOLFUSDM",
    "quality": "high",
    "fetchedAt": "2026-03-08T23:10:39.711Z"
  },
  {
    "date": "2011-03-01",
    "price": 17.029845,
    "unit": "usd/kilogram",
    "source": "fred",
    "sourceId": "PWOOLFUSDM",
    "quality": "high",
    "fetchedAt": "2026-03-08T23:10:39.711Z"
  },
  {
    "date": "2011-02-01",
    "price": 16.331143,
    "unit": "usd/kilogram",
    "source": "fred",
    "sourceId": "PWOOLFUSDM",
    "quality": "high",
    "fetchedAt": "2026-03-08T23:10:39.711Z"
  },
  {
    "date": "2011-01-01",
    "price": 15.493972,
    "unit": "usd/kilogram",
    "source": "fred",
    "sourceId": "PWOOLFUSDM",
    "quality": "high",
    "fetchedAt": "2026-03-08T23:10:39.711Z"
  },
  {
    "date": "2010-12-01",
    "price": 12.661738,
    "unit": "usd/kilogram",
    "source": "fred",
    "sourceId": "PWOOLFUSDM",
    "quality": "high",
    "fetchedAt": "2026-03-08T23:10:39.711Z"
  },
  {
    "date": "2010-11-01",
    "price": 11.689344,
    "unit": "usd/kilogram",
    "source": "fred",
    "sourceId": "PWOOLFUSDM",
    "quality": "high",
    "fetchedAt": "2026-03-08T23:10:39.711Z"
  },
  {
    "date": "2010-10-01",
    "price": 10.847161,
    "unit": "usd/kilogram",
    "source": "fred",
    "sourceId": "PWOOLFUSDM",
    "quality": "high",
    "fetchedAt": "2026-03-08T23:10:39.711Z"
  },
  {
    "date": "2010-09-01",
    "price": 9.882309,
    "unit": "usd/kilogram",
    "source": "fred",
    "sourceId": "PWOOLFUSDM",
    "quality": "high",
    "fetchedAt": "2026-03-08T23:10:39.711Z"
  },
  {
    "date": "2010-08-01",
    "price": 9.355864,
    "unit": "usd/kilogram",
    "source": "fred",
    "sourceId": "PWOOLFUSDM",
    "quality": "high",
    "fetchedAt": "2026-03-08T23:10:39.711Z"
  },
  {
    "date": "2010-07-01",
    "price": 9.183548,
    "unit": "usd/kilogram",
    "source": "fred",
    "sourceId": "PWOOLFUSDM",
    "quality": "high",
    "fetchedAt": "2026-03-08T23:10:39.711Z"
  },
  {
    "date": "2010-06-01",
    "price": 9.195192,
    "unit": "usd/kilogram",
    "source": "fred",
    "sourceId": "PWOOLFUSDM",
    "quality": "high",
    "fetchedAt": "2026-03-08T23:10:39.711Z"
  },
  {
    "date": "2010-05-01",
    "price": 9.194291,
    "unit": "usd/kilogram",
    "source": "fred",
    "sourceId": "PWOOLFUSDM",
    "quality": "high",
    "fetchedAt": "2026-03-08T23:10:39.711Z"
  },
  {
    "date": "2010-04-01",
    "price": 9.918256,
    "unit": "usd/kilogram",
    "source": "fred",
    "sourceId": "PWOOLFUSDM",
    "quality": "high",
    "fetchedAt": "2026-03-08T23:10:39.711Z"
  },
  {
    "date": "2010-03-01",
    "price": 10.038649,
    "unit": "usd/kilogram",
    "source": "fred",
    "sourceId": "PWOOLFUSDM",
    "quality": "high",
    "fetchedAt": "2026-03-08T23:10:39.711Z"
  },
  {
    "date": "2010-02-01",
    "price": 9.728095,
    "unit": "usd/kilogram",
    "source": "fred",
    "sourceId": "PWOOLFUSDM",
    "quality": "high",
    "fetchedAt": "2026-03-08T23:10:39.711Z"
  },
  {
    "date": "2010-01-01",
    "price": 10.032156,
    "unit": "usd/kilogram",
    "source": "fred",
    "sourceId": "PWOOLFUSDM",
    "quality": "high",
    "fetchedAt": "2026-03-08T23:10:39.711Z"
  },
  {
    "date": "2009-12-01",
    "price": 9.700835,
    "unit": "usd/kilogram",
    "source": "fred",
    "sourceId": "PWOOLFUSDM",
    "quality": "high",
    "fetchedAt": "2026-03-08T23:10:39.711Z"
  },
  {
    "date": "2009-11-01",
    "price": 9.539493,
    "unit": "usd/kilogram",
    "source": "fred",
    "sourceId": "PWOOLFUSDM",
    "quality": "high",
    "fetchedAt": "2026-03-08T23:10:39.711Z"
  },
  {
    "date": "2009-10-01",
    "price": 9.448493,
    "unit": "usd/kilogram",
    "source": "fred",
    "sourceId": "PWOOLFUSDM",
    "quality": "high",
    "fetchedAt": "2026-03-08T23:10:39.711Z"
  },
  {
    "date": "2009-09-01",
    "price": 8.675835,
    "unit": "usd/kilogram",
    "source": "fred",
    "sourceId": "PWOOLFUSDM",
    "quality": "high",
    "fetchedAt": "2026-03-08T23:10:39.711Z"
  },
  {
    "date": "2009-08-01",
    "price": 8.225666,
    "unit": "usd/kilogram",
    "source": "fred",
    "sourceId": "PWOOLFUSDM",
    "quality": "high",
    "fetchedAt": "2026-03-08T23:10:39.711Z"
  },
  {
    "date": "2009-07-01",
    "price": 7.636199,
    "unit": "usd/kilogram",
    "source": "fred",
    "sourceId": "PWOOLFUSDM",
    "quality": "high",
    "fetchedAt": "2026-03-08T23:10:39.711Z"
  },
  {
    "date": "2009-06-01",
    "price": 7.417344,
    "unit": "usd/kilogram",
    "source": "fred",
    "sourceId": "PWOOLFUSDM",
    "quality": "high",
    "fetchedAt": "2026-03-08T23:10:39.711Z"
  },
  {
    "date": "2009-05-01",
    "price": 7.613371,
    "unit": "usd/kilogram",
    "source": "fred",
    "sourceId": "PWOOLFUSDM",
    "quality": "high",
    "fetchedAt": "2026-03-08T23:10:39.711Z"
  },
  {
    "date": "2009-04-01",
    "price": 6.868628,
    "unit": "usd/kilogram",
    "source": "fred",
    "sourceId": "PWOOLFUSDM",
    "quality": "high",
    "fetchedAt": "2026-03-08T23:10:39.711Z"
  },
  {
    "date": "2009-03-01",
    "price": 6.171481,
    "unit": "usd/kilogram",
    "source": "fred",
    "sourceId": "PWOOLFUSDM",
    "quality": "high",
    "fetchedAt": "2026-03-08T23:10:39.711Z"
  },
  {
    "date": "2009-02-01",
    "price": 5.862595,
    "unit": "usd/kilogram",
    "source": "fred",
    "sourceId": "PWOOLFUSDM",
    "quality": "high",
    "fetchedAt": "2026-03-08T23:10:39.711Z"
  },
  {
    "date": "2009-01-01",
    "price": 6.233158,
    "unit": "usd/kilogram",
    "source": "fred",
    "sourceId": "PWOOLFUSDM",
    "quality": "high",
    "fetchedAt": "2026-03-08T23:10:39.711Z"
  },
  {
    "date": "2008-12-01",
    "price": 6.663869,
    "unit": "usd/kilogram",
    "source": "fred",
    "sourceId": "PWOOLFUSDM",
    "quality": "high",
    "fetchedAt": "2026-03-08T23:10:39.711Z"
  },
  {
    "date": "2008-11-01",
    "price": 6.465798,
    "unit": "usd/kilogram",
    "source": "fred",
    "sourceId": "PWOOLFUSDM",
    "quality": "high",
    "fetchedAt": "2026-03-08T23:10:39.711Z"
  },
  {
    "date": "2008-10-01",
    "price": 7.349064,
    "unit": "usd/kilogram",
    "source": "fred",
    "sourceId": "PWOOLFUSDM",
    "quality": "high",
    "fetchedAt": "2026-03-08T23:10:39.711Z"
  },
  {
    "date": "2008-09-01",
    "price": 8.967923,
    "unit": "usd/kilogram",
    "source": "fred",
    "sourceId": "PWOOLFUSDM",
    "quality": "high",
    "fetchedAt": "2026-03-08T23:10:39.711Z"
  },
  {
    "date": "2008-08-01",
    "price": 9.417128,
    "unit": "usd/kilogram",
    "source": "fred",
    "sourceId": "PWOOLFUSDM",
    "quality": "high",
    "fetchedAt": "2026-03-08T23:10:39.711Z"
  },
  {
    "date": "2008-07-01",
    "price": 10.479734,
    "unit": "usd/kilogram",
    "source": "fred",
    "sourceId": "PWOOLFUSDM",
    "quality": "high",
    "fetchedAt": "2026-03-08T23:10:39.711Z"
  },
  {
    "date": "2008-06-01",
    "price": 10.410961,
    "unit": "usd/kilogram",
    "source": "fred",
    "sourceId": "PWOOLFUSDM",
    "quality": "high",
    "fetchedAt": "2026-03-08T23:10:39.711Z"
  },
  {
    "date": "2008-05-01",
    "price": 10.624416,
    "unit": "usd/kilogram",
    "source": "fred",
    "sourceId": "PWOOLFUSDM",
    "quality": "high",
    "fetchedAt": "2026-03-08T23:10:39.711Z"
  },
  {
    "date": "2008-04-01",
    "price": 11.298394,
    "unit": "usd/kilogram",
    "source": "fred",
    "sourceId": "PWOOLFUSDM",
    "quality": "high",
    "fetchedAt": "2026-03-08T23:10:39.711Z"
  },
  {
    "date": "2008-03-01",
    "price": 11.35995,
    "unit": "usd/kilogram",
    "source": "fred",
    "sourceId": "PWOOLFUSDM",
    "quality": "high",
    "fetchedAt": "2026-03-08T23:10:39.711Z"
  },
  {
    "date": "2008-02-01",
    "price": 11.542529,
    "unit": "usd/kilogram",
    "source": "fred",
    "sourceId": "PWOOLFUSDM",
    "quality": "high",
    "fetchedAt": "2026-03-08T23:10:39.711Z"
  },
  {
    "date": "2008-01-01",
    "price": 11.57372,
    "unit": "usd/kilogram",
    "source": "fred",
    "sourceId": "PWOOLFUSDM",
    "quality": "high",
    "fetchedAt": "2026-03-08T23:10:39.711Z"
  },
  {
    "date": "2007-12-01",
    "price": 10.972649,
    "unit": "usd/kilogram",
    "source": "fred",
    "sourceId": "PWOOLFUSDM",
    "quality": "high",
    "fetchedAt": "2026-03-08T23:10:39.711Z"
  },
  {
    "date": "2007-11-01",
    "price": 11.027051,
    "unit": "usd/kilogram",
    "source": "fred",
    "sourceId": "PWOOLFUSDM",
    "quality": "high",
    "fetchedAt": "2026-03-08T23:10:39.711Z"
  },
  {
    "date": "2007-10-01",
    "price": 10.806388,
    "unit": "usd/kilogram",
    "source": "fred",
    "sourceId": "PWOOLFUSDM",
    "quality": "high",
    "fetchedAt": "2026-03-08T23:10:39.711Z"
  },
  {
    "date": "2007-09-01",
    "price": 9.430778,
    "unit": "usd/kilogram",
    "source": "fred",
    "sourceId": "PWOOLFUSDM",
    "quality": "high",
    "fetchedAt": "2026-03-08T23:10:39.711Z"
  },
  {
    "date": "2007-08-01",
    "price": 9.1411,
    "unit": "usd/kilogram",
    "source": "fred",
    "sourceId": "PWOOLFUSDM",
    "quality": "high",
    "fetchedAt": "2026-03-08T23:10:39.711Z"
  },
  {
    "date": "2007-07-01",
    "price": 9.363393,
    "unit": "usd/kilogram",
    "source": "fred",
    "sourceId": "PWOOLFUSDM",
    "quality": "high",
    "fetchedAt": "2026-03-08T23:10:39.711Z"
  },
  {
    "date": "2007-06-01",
    "price": 9.877324,
    "unit": "usd/kilogram",
    "source": "fred",
    "sourceId": "PWOOLFUSDM",
    "quality": "high",
    "fetchedAt": "2026-03-08T23:10:39.711Z"
  },
  {
    "date": "2007-05-01",
    "price": 9.890814,
    "unit": "usd/kilogram",
    "source": "fred",
    "sourceId": "PWOOLFUSDM",
    "quality": "high",
    "fetchedAt": "2026-03-08T23:10:39.711Z"
  },
  {
    "date": "2007-04-01",
    "price": 9.403694,
    "unit": "usd/kilogram",
    "source": "fred",
    "sourceId": "PWOOLFUSDM",
    "quality": "high",
    "fetchedAt": "2026-03-08T23:10:39.711Z"
  },
  {
    "date": "2007-03-01",
    "price": 9.140159,
    "unit": "usd/kilogram",
    "source": "fred",
    "sourceId": "PWOOLFUSDM",
    "quality": "high",
    "fetchedAt": "2026-03-08T23:10:39.711Z"
  },
  {
    "date": "2007-02-01",
    "price": 8.756157,
    "unit": "usd/kilogram",
    "source": "fred",
    "sourceId": "PWOOLFUSDM",
    "quality": "high",
    "fetchedAt": "2026-03-08T23:10:39.711Z"
  },
  {
    "date": "2007-01-01",
    "price": 8.936554,
    "unit": "usd/kilogram",
    "source": "fred",
    "sourceId": "PWOOLFUSDM",
    "quality": "high",
    "fetchedAt": "2026-03-08T23:10:39.711Z"
  },
  {
    "date": "2006-12-01",
    "price": 7.906884,
    "unit": "usd/kilogram",
    "source": "fred",
    "sourceId": "PWOOLFUSDM",
    "quality": "high",
    "fetchedAt": "2026-03-08T23:10:39.711Z"
  },
  {
    "date": "2006-11-01",
    "price": 7.903351,
    "unit": "usd/kilogram",
    "source": "fred",
    "sourceId": "PWOOLFUSDM",
    "quality": "high",
    "fetchedAt": "2026-03-08T23:10:39.711Z"
  },
  {
    "date": "2006-10-01",
    "price": 6.907368,
    "unit": "usd/kilogram",
    "source": "fred",
    "sourceId": "PWOOLFUSDM",
    "quality": "high",
    "fetchedAt": "2026-03-08T23:10:39.711Z"
  },
  {
    "date": "2006-09-01",
    "price": 7.049136,
    "unit": "usd/kilogram",
    "source": "fred",
    "sourceId": "PWOOLFUSDM",
    "quality": "high",
    "fetchedAt": "2026-03-08T23:10:39.711Z"
  },
  {
    "date": "2006-08-01",
    "price": 7.175636,
    "unit": "usd/kilogram",
    "source": "fred",
    "sourceId": "PWOOLFUSDM",
    "quality": "high",
    "fetchedAt": "2026-03-08T23:10:39.711Z"
  },
  {
    "date": "2006-07-01",
    "price": 7.048455,
    "unit": "usd/kilogram",
    "source": "fred",
    "sourceId": "PWOOLFUSDM",
    "quality": "high",
    "fetchedAt": "2026-03-08T23:10:39.711Z"
  },
  {
    "date": "2006-06-01",
    "price": 7.144923,
    "unit": "usd/kilogram",
    "source": "fred",
    "sourceId": "PWOOLFUSDM",
    "quality": "high",
    "fetchedAt": "2026-03-08T23:10:39.711Z"
  },
  {
    "date": "2006-05-01",
    "price": 7.322484,
    "unit": "usd/kilogram",
    "source": "fred",
    "sourceId": "PWOOLFUSDM",
    "quality": "high",
    "fetchedAt": "2026-03-08T23:10:39.711Z"
  },
  {
    "date": "2006-04-01",
    "price": 6.976961,
    "unit": "usd/kilogram",
    "source": "fred",
    "sourceId": "PWOOLFUSDM",
    "quality": "high",
    "fetchedAt": "2026-03-08T23:10:39.711Z"
  },
  {
    "date": "2006-03-01",
    "price": 6.987498,
    "unit": "usd/kilogram",
    "source": "fred",
    "sourceId": "PWOOLFUSDM",
    "quality": "high",
    "fetchedAt": "2026-03-08T23:10:39.711Z"
  },
  {
    "date": "2006-02-01",
    "price": 7.097268,
    "unit": "usd/kilogram",
    "source": "fred",
    "sourceId": "PWOOLFUSDM",
    "quality": "high",
    "fetchedAt": "2026-03-08T23:10:39.711Z"
  },
  {
    "date": "2006-01-01",
    "price": 6.391667,
    "unit": "usd/kilogram",
    "source": "fred",
    "sourceId": "PWOOLFUSDM",
    "quality": "high",
    "fetchedAt": "2026-03-08T23:10:39.711Z"
  },
  {
    "date": "2005-12-01",
    "price": 5.888329,
    "unit": "usd/kilogram",
    "source": "fred",
    "sourceId": "PWOOLFUSDM",
    "quality": "high",
    "fetchedAt": "2026-03-08T23:10:39.711Z"
  },
  {
    "date": "2005-11-01",
    "price": 5.936913,
    "unit": "usd/kilogram",
    "source": "fred",
    "sourceId": "PWOOLFUSDM",
    "quality": "high",
    "fetchedAt": "2026-03-08T23:10:39.711Z"
  },
  {
    "date": "2005-10-01",
    "price": 6.225709,
    "unit": "usd/kilogram",
    "source": "fred",
    "sourceId": "PWOOLFUSDM",
    "quality": "high",
    "fetchedAt": "2026-03-08T23:10:39.711Z"
  },
  {
    "date": "2005-09-01",
    "price": 6.474023,
    "unit": "usd/kilogram",
    "source": "fred",
    "sourceId": "PWOOLFUSDM",
    "quality": "high",
    "fetchedAt": "2026-03-08T23:10:39.711Z"
  },
  {
    "date": "2005-08-01",
    "price": 6.647468,
    "unit": "usd/kilogram",
    "source": "fred",
    "sourceId": "PWOOLFUSDM",
    "quality": "high",
    "fetchedAt": "2026-03-08T23:10:39.711Z"
  },
  {
    "date": "2005-07-01",
    "price": 6.816321,
    "unit": "usd/kilogram",
    "source": "fred",
    "sourceId": "PWOOLFUSDM",
    "quality": "high",
    "fetchedAt": "2026-03-08T23:10:39.711Z"
  },
  {
    "date": "2005-06-01",
    "price": 6.846006,
    "unit": "usd/kilogram",
    "source": "fred",
    "sourceId": "PWOOLFUSDM",
    "quality": "high",
    "fetchedAt": "2026-03-08T23:10:39.711Z"
  },
  {
    "date": "2005-05-01",
    "price": 7.171271,
    "unit": "usd/kilogram",
    "source": "fred",
    "sourceId": "PWOOLFUSDM",
    "quality": "high",
    "fetchedAt": "2026-03-08T23:10:39.711Z"
  },
  {
    "date": "2005-04-01",
    "price": 7.291754,
    "unit": "usd/kilogram",
    "source": "fred",
    "sourceId": "PWOOLFUSDM",
    "quality": "high",
    "fetchedAt": "2026-03-08T23:10:39.711Z"
  },
  {
    "date": "2005-03-01",
    "price": 7.28442,
    "unit": "usd/kilogram",
    "source": "fred",
    "sourceId": "PWOOLFUSDM",
    "quality": "high",
    "fetchedAt": "2026-03-08T23:10:39.711Z"
  },
  {
    "date": "2005-02-01",
    "price": 7.346866,
    "unit": "usd/kilogram",
    "source": "fred",
    "sourceId": "PWOOLFUSDM",
    "quality": "high",
    "fetchedAt": "2026-03-08T23:10:39.711Z"
  },
  {
    "date": "2005-01-01",
    "price": 7.301624,
    "unit": "usd/kilogram",
    "source": "fred",
    "sourceId": "PWOOLFUSDM",
    "quality": "high",
    "fetchedAt": "2026-03-08T23:10:39.711Z"
  },
  {
    "date": "2004-12-01",
    "price": 7.156118,
    "unit": "usd/kilogram",
    "source": "fred",
    "sourceId": "PWOOLFUSDM",
    "quality": "high",
    "fetchedAt": "2026-03-08T23:10:39.711Z"
  },
  {
    "date": "2004-11-01",
    "price": 7.360271,
    "unit": "usd/kilogram",
    "source": "fred",
    "sourceId": "PWOOLFUSDM",
    "quality": "high",
    "fetchedAt": "2026-03-08T23:10:39.711Z"
  },
  {
    "date": "2004-10-01",
    "price": 7.189581,
    "unit": "usd/kilogram",
    "source": "fred",
    "sourceId": "PWOOLFUSDM",
    "quality": "high",
    "fetchedAt": "2026-03-08T23:10:39.711Z"
  },
  {
    "date": "2004-09-01",
    "price": 7.036046,
    "unit": "usd/kilogram",
    "source": "fred",
    "sourceId": "PWOOLFUSDM",
    "quality": "high",
    "fetchedAt": "2026-03-08T23:10:39.711Z"
  },
  {
    "date": "2004-08-01",
    "price": 7.143498,
    "unit": "usd/kilogram",
    "source": "fred",
    "sourceId": "PWOOLFUSDM",
    "quality": "high",
    "fetchedAt": "2026-03-08T23:10:39.711Z"
  },
  {
    "date": "2004-07-01",
    "price": 7.234445,
    "unit": "usd/kilogram",
    "source": "fred",
    "sourceId": "PWOOLFUSDM",
    "quality": "high",
    "fetchedAt": "2026-03-08T23:10:39.711Z"
  },
  {
    "date": "2004-06-01",
    "price": 7.084999,
    "unit": "usd/kilogram",
    "source": "fred",
    "sourceId": "PWOOLFUSDM",
    "quality": "high",
    "fetchedAt": "2026-03-08T23:10:39.711Z"
  },
  {
    "date": "2004-05-01",
    "price": 7.01883,
    "unit": "usd/kilogram",
    "source": "fred",
    "sourceId": "PWOOLFUSDM",
    "quality": "high",
    "fetchedAt": "2026-03-08T23:10:39.711Z"
  },
  {
    "date": "2004-04-01",
    "price": 7.061176,
    "unit": "usd/kilogram",
    "source": "fred",
    "sourceId": "PWOOLFUSDM",
    "quality": "high",
    "fetchedAt": "2026-03-08T23:10:39.711Z"
  },
  {
    "date": "2004-03-01",
    "price": 7.087456,
    "unit": "usd/kilogram",
    "source": "fred",
    "sourceId": "PWOOLFUSDM",
    "quality": "high",
    "fetchedAt": "2026-03-08T23:10:39.711Z"
  },
  {
    "date": "2004-02-01",
    "price": 7.215169,
    "unit": "usd/kilogram",
    "source": "fred",
    "sourceId": "PWOOLFUSDM",
    "quality": "high",
    "fetchedAt": "2026-03-08T23:10:39.711Z"
  },
  {
    "date": "2004-01-01",
    "price": 7.353856,
    "unit": "usd/kilogram",
    "source": "fred",
    "sourceId": "PWOOLFUSDM",
    "quality": "high",
    "fetchedAt": "2026-03-08T23:10:39.711Z"
  },
  {
    "date": "2003-12-01",
    "price": 6.615545,
    "unit": "usd/kilogram",
    "source": "fred",
    "sourceId": "PWOOLFUSDM",
    "quality": "high",
    "fetchedAt": "2026-03-08T23:10:39.711Z"
  },
  {
    "date": "2003-11-01",
    "price": 6.465165,
    "unit": "usd/kilogram",
    "source": "fred",
    "sourceId": "PWOOLFUSDM",
    "quality": "high",
    "fetchedAt": "2026-03-08T23:10:39.711Z"
  },
  {
    "date": "2003-10-01",
    "price": 6.643872,
    "unit": "usd/kilogram",
    "source": "fred",
    "sourceId": "PWOOLFUSDM",
    "quality": "high",
    "fetchedAt": "2026-03-08T23:10:39.711Z"
  },
  {
    "date": "2003-09-01",
    "price": 6.74518,
    "unit": "usd/kilogram",
    "source": "fred",
    "sourceId": "PWOOLFUSDM",
    "quality": "high",
    "fetchedAt": "2026-03-08T23:10:39.711Z"
  },
  {
    "date": "2003-08-01",
    "price": 6.708659,
    "unit": "usd/kilogram",
    "source": "fred",
    "sourceId": "PWOOLFUSDM",
    "quality": "high",
    "fetchedAt": "2026-03-08T23:10:39.711Z"
  },
  {
    "date": "2003-07-01",
    "price": 6.629372,
    "unit": "usd/kilogram",
    "source": "fred",
    "sourceId": "PWOOLFUSDM",
    "quality": "high",
    "fetchedAt": "2026-03-08T23:10:39.711Z"
  },
  {
    "date": "2003-06-01",
    "price": 7.003522,
    "unit": "usd/kilogram",
    "source": "fred",
    "sourceId": "PWOOLFUSDM",
    "quality": "high",
    "fetchedAt": "2026-03-08T23:10:39.711Z"
  },
  {
    "date": "2003-05-01",
    "price": 6.808287,
    "unit": "usd/kilogram",
    "source": "fred",
    "sourceId": "PWOOLFUSDM",
    "quality": "high",
    "fetchedAt": "2026-03-08T23:10:39.711Z"
  },
  {
    "date": "2003-04-01",
    "price": 7.319749,
    "unit": "usd/kilogram",
    "source": "fred",
    "sourceId": "PWOOLFUSDM",
    "quality": "high",
    "fetchedAt": "2026-03-08T23:10:39.711Z"
  },
  {
    "date": "2003-03-01",
    "price": 7.352717,
    "unit": "usd/kilogram",
    "source": "fred",
    "sourceId": "PWOOLFUSDM",
    "quality": "high",
    "fetchedAt": "2026-03-08T23:10:39.711Z"
  },
  {
    "date": "2003-02-01",
    "price": 7.77266,
    "unit": "usd/kilogram",
    "source": "fred",
    "sourceId": "PWOOLFUSDM",
    "quality": "high",
    "fetchedAt": "2026-03-08T23:10:39.711Z"
  },
  {
    "date": "2003-01-01",
    "price": 7.947209,
    "unit": "usd/kilogram",
    "source": "fred",
    "sourceId": "PWOOLFUSDM",
    "quality": "high",
    "fetchedAt": "2026-03-08T23:10:39.710Z"
  }
]